redcap/__init__.py
redcap/conftest.py
redcap/methods/__init__.py
redcap/methods/arms.py
redcap/methods/base.py
redcap/methods/data_access_groups.py
redcap/methods/events.py
redcap/methods/field_names.py
redcap/methods/file_repository.py
redcap/methods/files.py
redcap/methods/instruments.py
redcap/methods/logging.py
redcap/methods/metadata.py
redcap/methods/project_info.py
redcap/methods/records.py
redcap/methods/repeating.py
redcap/methods/reports.py
redcap/methods/surveys.py
redcap/methods/user_roles.py
redcap/methods/users.py
redcap/methods/version.py
redcap/project.py
redcap/py.typed
redcap/request.py
pycap-2.7.0.dist-info/LICENSE
pycap-2.7.0.dist-info/WHEEL
pycap-2.7.0.dist-info/METADATA
pycap-2.7.0.dist-info/RECORD
