Metadata-Version: 2.1
Name: pycap
Version: 2.7.0
Summary: PyCap: Python interface to REDCap
Home-page: https://github.com/redcap-tools/PyCap
License: MIT
Author: Scott Burns
Author-email: scott.s.burns@gmail.com
Maintainer: Paul Wildenhain
Maintainer-email: pwildenhain@gmail.com
Requires-Python: >=3.10,<4.0
Classifier: Development Status :: 5 - Production/Stable
Classifier: Intended Audience :: Developers
Classifier: Intended Audience :: Science/Research
Classifier: License :: OSI Approved
Classifier: License :: OSI Approved :: MIT License
Classifier: Operating System :: MacOS
Classifier: Operating System :: Microsoft :: Windows
Classifier: Operating System :: POSIX
Classifier: Operating System :: Unix
Classifier: Programming Language :: Python
Classifier: Programming Language :: Python :: 3
Classifier: Programming Language :: Python :: 3.10
Classifier: Programming Language :: Python :: 3.11
Classifier: Topic :: Scientific/Engineering
Classifier: Topic :: Software Development
Provides-Extra: data-science
Requires-Dist: pandas (>=2.0.0,<3.0.0) ; extra == "data-science"
Requires-Dist: requests (>=2.20,<3.0)
Requires-Dist: semantic-version (>=2.8.5,<3.0.0)
Project-URL: Documentation, http://redcap-tools.github.io/PyCap/
Project-URL: Repository, https://github.com/redcap-tools/PyCap
